psite_annotation/__init__.py
psite_annotation/annotators/__init__.py
psite_annotation/annotators/annotator_base.py
psite_annotation/annotators/clinical_basket.py
psite_annotation/annotators/domain.py
psite_annotation/annotators/in_vitro_kinases.py
psite_annotation/annotators/kinase_library.py
psite_annotation/annotators/modified_sequence_aggregation.py
psite_annotation/annotators/modified_sequence_group.py
psite_annotation/annotators/motif.py
psite_annotation/annotators/peptide_position.py
psite_annotation/annotators/psp_kinases.py
psite_annotation/annotators/psp_regulatory.py
psite_annotation/annotators/psp_studies.py
psite_annotation/annotators/ptm_turnover.py
psite_annotation/annotators/separated_strings.py
psite_annotation/annotators/site_sequence_context.py
psite_annotation/config.py
psite_annotation/functional_annotation.py
psite_annotation-0.7.2.dist-info/LICENSE
psite_annotation-0.7.2.dist-info/METADATA
psite_annotation-0.7.2.dist-info/WHEEL
psite_annotation-0.7.2.dist-info/RECORD
