Metadata-Version: 2.1
Name: psite-annotation
Version: 0.7.2
Summary: Module for annotating p-sites based on resources such as PhosphoSitePlus
License: Apache-2.0
Author: Matthew The
Author-email: matthew.the@tum.de
Requires-Python: >=3.9,<3.13
Classifier: License :: OSI Approved :: Apache Software License
Classifier: Programming Language :: Python :: 3
Classifier: Programming Language :: Python :: 3.9
Classifier: Programming Language :: Python :: 3.10
Classifier: Programming Language :: Python :: 3.11
Classifier: Programming Language :: Python :: 3.12
Requires-Dist: config-path (==1.0.3)
Requires-Dist: numpy (>=1.18.1,<3.0)
Requires-Dist: pandas (>=1.3.0)
Requires-Dist: scipy (>=1.11.3,<2.0.0)
